{
  "packId": "igko-grade9-mock-01",
  "exam": "igko",
  "grade": 9,
  "mode": "mock",
  "title": "IGKO Grade 9 Mock Test 1",
  "durationMinutes": 30,
  "questionIds": [
    "igko-g9-plants-and-animals-0001",
    "igko-g9-plants-and-animals-0002",
    "igko-g9-plants-and-animals-0003",
    "igko-g9-plants-and-animals-0004",
    "igko-g9-plants-and-animals-0005",
    "igko-g9-plants-and-animals-0006",
    "igko-g9-plants-and-animals-0007",
    "igko-g9-plants-and-animals-0008",
    "igko-g9-plants-and-animals-0009",
    "igko-g9-plants-and-animals-0010",
    "igko-g9-plants-and-animals-0011",
    "igko-g9-plants-and-animals-0012",
    "igko-g9-plants-and-animals-0013",
    "igko-g9-plants-and-animals-0014",
    "igko-g9-plants-and-animals-0015",
    "igko-g9-plants-and-animals-0016",
    "igko-g9-plants-and-animals-0017",
    "igko-g9-plants-and-animals-0018",
    "igko-g9-plants-and-animals-0019",
    "igko-g9-plants-and-animals-0020",
    "igko-g9-plants-and-animals-0021",
    "igko-g9-plants-and-animals-0022",
    "igko-g9-plants-and-animals-0023",
    "igko-g9-plants-and-animals-0024",
    "igko-g9-plants-and-animals-0025"
  ]
}
