{
  "packId": "ieo-grade7-mock-02",
  "exam": "ieo",
  "grade": 7,
  "mode": "mock",
  "title": "IEO Mock Test 2",
  "durationMinutes": 30,
  "questionIds": [
    "ieo-g7-vocabulary-0070",
    "ieo-g7-comprehension-0094",
    "ieo-g7-grammar-0013",
    "ieo-g7-vocabulary-0047",
    "ieo-g7-grammar-0006",
    "ieo-g7-comprehension-0081",
    "ieo-g7-vocabulary-0045",
    "ieo-g7-vocabulary-0046",
    "ieo-g7-vocabulary-0053",
    "ieo-g7-comprehension-0089",
    "ieo-g7-vocabulary-0041",
    "ieo-g7-comprehension-0088",
    "ieo-g7-comprehension-0080",
    "ieo-g7-grammar-0007",
    "ieo-g7-vocabulary-0073",
    "ieo-g7-comprehension-0079",
    "ieo-g7-grammar-0011",
    "ieo-g7-vocabulary-0057",
    "ieo-g7-grammar-0040",
    "ieo-g7-vocabulary-0060",
    "ieo-g7-comprehension-0078",
    "ieo-g7-grammar-0016",
    "ieo-g7-grammar-0014",
    "ieo-g7-grammar-0030",
    "ieo-g7-grammar-0039"
  ]
}