{
  "packId": "ieo-grade1-mock-02",
  "exam": "ieo",
  "grade": 1,
  "mode": "mock",
  "title": "IEO Mock Test 2",
  "durationMinutes": 30,
  "questionIds": [
    "ieo-g1-sentence-formation-0098",
    "ieo-g1-simple-grammar-0065",
    "ieo-g1-simple-grammar-0058",
    "ieo-g1-vocabulary-0034",
    "ieo-g1-simple-grammar-0047",
    "ieo-g1-sentence-formation-0099",
    "ieo-g1-simple-grammar-0049",
    "ieo-g1-simple-grammar-0068",
    "ieo-g1-vocabulary-0029",
    "ieo-g1-sentence-formation-0091",
    "ieo-g1-simple-grammar-0064",
    "ieo-g1-vocabulary-0036",
    "ieo-g1-simple-grammar-0072",
    "ieo-g1-simple-grammar-0050",
    "ieo-g1-simple-grammar-0077",
    "ieo-g1-simple-grammar-0074",
    "ieo-g1-vocabulary-0006",
    "ieo-g1-simple-grammar-0053",
    "ieo-g1-vocabulary-0017",
    "ieo-g1-simple-grammar-0067",
    "ieo-g1-sentence-formation-0088",
    "ieo-g1-vocabulary-0030",
    "ieo-g1-sentence-formation-0086",
    "ieo-g1-vocabulary-0022",
    "ieo-g1-simple-grammar-0044"
  ]
}